project/m4/rtl/compute_core.sv
`timescale 1ns/1ps

module mac_array (
  input  wire        clk, rst, en,
  input  wire signed [7:0]  a0,a1,a2,a3,a4,a5,a6,a7,a8,
  input  wire signed [7:0]  b0,b1,b2,b3,b4,b5,b6,b7,b8,
  output reg  signed [31:0] acc_out
);
  wire signed [15:0] p0,p1,p2,p3,p4,p5,p6,p7,p8;
  assign p0=$signed(a0)*$signed(b0); assign p1=$signed(a1)*$signed(b1);
  assign p2=$signed(a2)*$signed(b2); assign p3=$signed(a3)*$signed(b3);
  assign p4=$signed(a4)*$signed(b4); assign p5=$signed(a5)*$signed(b5);
  assign p6=$signed(a6)*$signed(b6); assign p7=$signed(a7)*$signed(b7);
  assign p8=$signed(a8)*$signed(b8);
  always @(posedge clk) begin
    if (rst) acc_out<=32'sd0;
    else if (en)
      acc_out<={{16{p0[15]}},p0}+{{16{p1[15]}},p1}
              +{{16{p2[15]}},p2}+{{16{p3[15]}},p3}
              +{{16{p4[15]}},p4}+{{16{p5[15]}},p5}
              +{{16{p6[15]}},p6}+{{16{p7[15]}},p7}
              +{{16{p8[15]}},p8};
  end
endmodule

module requantizer (
  input  wire        clk, rst, valid_in,
  input  wire signed [31:0] in_data,
  input  wire [4:0]  shift,
  output reg  signed [7:0]  out_data
);
  wire signed [31:0] shifted;
  assign shifted = in_data>>>shift;
  always @(posedge clk) begin
    if (rst) out_data<=8'sd0;
    else if (valid_in) begin
      if      (shifted> 32'sd127) out_data<= 8'sd127;
      else if (shifted<-32'sd128) out_data<=-8'sd128;
      else                        out_data<=shifted[7:0];
    end
  end
endmodule

project/m4/rtl/top.sv
`timescale 1ns/1ps
module conv2d_top #(
  parameter DATA_WIDTH=8, parameter ACC_WIDTH=32,
  parameter C_IN=1, parameter C_OUT=1,
  parameter H_IN=5, parameter W_IN=5,
  parameter K=3, parameter H_OUT=1, parameter W_OUT=1,
  parameter SHIFT_BITS=0
)(
  input  wire        clk, rst,
  input  wire [31:0] s_axil_awaddr,
  input  wire        s_axil_awvalid,
  output reg         s_axil_awready,
  input  wire [31:0] s_axil_wdata,
  input  wire [3:0]  s_axil_wstrb,
  input  wire        s_axil_wvalid,
  output reg         s_axil_wready,
  output reg  [1:0]  s_axil_bresp,
  output reg         s_axil_bvalid,
  input  wire        s_axil_bready,
  input  wire [31:0] s_axil_araddr,
  input  wire        s_axil_arvalid,
  output reg         s_axil_arready,
  output reg  [31:0] s_axil_rdata,
  output reg  [1:0]  s_axil_rresp,
  output reg         s_axil_rvalid,
  input  wire        s_axil_rready,
  output reg         done,
  output reg         busy
);
  localparam IDLE=3'd0,LOAD=3'd1,COMPUTE=3'd2,OUTPUT=3'd3,DONE_S=3'd4;
  reg [2:0] state, next_state;
  reg        reg_start;
  reg [31:0] reg_scale_shift;
  reg [4:0]  h_cnt, w_cnt;
  reg [2:0]  oc_cnt;
  reg        compute_valid;
  reg signed [7:0]  act_buf    [0:24];
  reg signed [7:0]  weight_buf [0:8];
  reg signed [31:0] bias_buf   [0:0];
  reg signed [7:0]  out_buf    [0:0];
  wire signed [7:0]  mac_a0,mac_a1,mac_a2,mac_a3,mac_a4;
  wire signed [7:0]  mac_a5,mac_a6,mac_a7,mac_a8;
  wire signed [7:0]  mac_b0,mac_b1,mac_b2,mac_b3,mac_b4;
  wire signed [7:0]  mac_b5,mac_b6,mac_b7,mac_b8;
  wire signed [31:0] mac_out;
  wire               mac_en;
  wire signed [31:0] req_in;
  wire signed [7:0]  req_out;
  wire               req_valid;
  wire compute_done;
  assign compute_done = compute_valid &&
                        (h_cnt==H_OUT-1) &&
                        (w_cnt==W_OUT-1) &&
                        (oc_cnt==C_OUT-1);
  always @(posedge clk) begin
    if (rst) state <= IDLE;
    else     state <= next_state;
  end
  always @(*) begin
    next_state = state;
    case (state)
      IDLE:    if (reg_start)    next_state = LOAD;
      LOAD:                      next_state = COMPUTE;
      COMPUTE: if (compute_done) next_state = OUTPUT;
      OUTPUT:                    next_state = DONE_S;
      DONE_S:  if (!reg_start)   next_state = IDLE;
      default:                   next_state = IDLE;
    endcase
  end
  always @(posedge clk) begin
    if (rst||state==IDLE||state==LOAD) begin
      h_cnt<=5'd0; w_cnt<=5'd0; oc_cnt<=3'd0; compute_valid<=1'b0;
    end else if (state==COMPUTE) begin
      compute_valid<=1'b1;
      if (oc_cnt==C_OUT-1) begin
        oc_cnt<=3'd0;
        if (w_cnt==W_OUT-1) begin
          w_cnt<=5'd0;
          if (h_cnt<H_OUT-1) h_cnt<=h_cnt+5'd1;
        end else w_cnt<=w_cnt+5'd1;
      end else oc_cnt<=oc_cnt+3'd1;
    end
  end
  always @(posedge clk) begin
    if (rst) begin done<=1'b0; busy<=1'b0; end
    else begin
      if ((state==OUTPUT)&&(next_state==DONE_S)) done<=1'b1;
      else if (state==IDLE) done<=1'b0;
      busy<=(state==COMPUTE);
    end
  end
  always @(posedge clk) begin
    if (rst)                out_buf[0]<=8'sd0;
    else if (state==DONE_S) out_buf[0]<=req_out;
  end
  always @(posedge clk) begin
    if (rst) begin
      reg_start<=1'b0; reg_scale_shift<=SHIFT_BITS;
      s_axil_awready<=1'b0; s_axil_wready<=1'b0;
      s_axil_bvalid<=1'b0;  s_axil_bresp<=2'b00;
      s_axil_arready<=1'b0; s_axil_rvalid<=1'b0;
      s_axil_rdata<=32'h0;  s_axil_rresp<=2'b00;
    end else begin
      s_axil_awready<=s_axil_awvalid;
      s_axil_wready <=s_axil_wvalid;
      if (s_axil_wvalid&&s_axil_wready) begin
        if      (s_axil_awaddr==32'h000) reg_start<=s_axil_wdata[0];
        else if (s_axil_awaddr==32'h008) reg_scale_shift<=s_axil_wdata;
        else if (s_axil_awaddr>=32'h100&&s_axil_awaddr<32'h164)
          act_buf[(s_axil_awaddr-32'h100)>>2]<=s_axil_wdata[7:0];
        else if (s_axil_awaddr>=32'h200&&s_axil_awaddr<32'h224)
          weight_buf[(s_axil_awaddr-32'h200)>>2]<=s_axil_wdata[7:0];
        else if (s_axil_awaddr==32'h300) bias_buf[0]<=s_axil_wdata;
        s_axil_bvalid<=1'b1;
      end else if (s_axil_bready) s_axil_bvalid<=1'b0;
      s_axil_arready<=s_axil_arvalid;
      if (s_axil_arvalid&&s_axil_arready) begin
        s_axil_rvalid<=1'b1;
        case (s_axil_araddr)
          32'h004: s_axil_rdata<={30'h0,busy,done};
          32'h400: s_axil_rdata<={{24{out_buf[0][7]}},out_buf[0]};
          default: s_axil_rdata<=32'hDEADBEEF;
        endcase
      end else if (s_axil_rready) s_axil_rvalid<=1'b0;
    end
  end
  wire [4:0] base0, base1, base2;
  assign base0 = h_cnt*W_IN + w_cnt;
  assign base1 = (h_cnt+5'd1)*W_IN + w_cnt;
  assign base2 = (h_cnt+5'd2)*W_IN + w_cnt;
  assign mac_a0=act_buf[base0];      assign mac_a1=act_buf[base0+5'd1];
  assign mac_a2=act_buf[base0+5'd2]; assign mac_a3=act_buf[base1];
  assign mac_a4=act_buf[base1+5'd1]; assign mac_a5=act_buf[base1+5'd2];
  assign mac_a6=act_buf[base2];      assign mac_a7=act_buf[base2+5'd1];
  assign mac_a8=act_buf[base2+5'd2];
  assign mac_b0=weight_buf[0]; assign mac_b1=weight_buf[1];
  assign mac_b2=weight_buf[2]; assign mac_b3=weight_buf[3];
  assign mac_b4=weight_buf[4]; assign mac_b5=weight_buf[5];
  assign mac_b6=weight_buf[6]; assign mac_b7=weight_buf[7];
  assign mac_b8=weight_buf[8];
  assign mac_en    = (state==COMPUTE);
  assign req_in    = mac_out + bias_buf[0];
  assign req_valid = (state==OUTPUT);
  mac_array u_mac (
    .clk(clk),.rst(rst),.en(mac_en),
    .a0(mac_a0),.a1(mac_a1),.a2(mac_a2),
    .a3(mac_a3),.a4(mac_a4),.a5(mac_a5),
    .a6(mac_a6),.a7(mac_a7),.a8(mac_a8),
    .b0(mac_b0),.b1(mac_b1),.b2(mac_b2),
    .b3(mac_b3),.b4(mac_b4),.b5(mac_b5),
    .b6(mac_b6),.b7(mac_b7),.b8(mac_b8),
    .acc_out(mac_out)
  );
  requantizer u_req (
    .clk(clk),.rst(rst),
    .in_data(req_in),
    .shift(reg_scale_shift[4:0]),
    .valid_in(req_valid),
    .out_data(req_out)
  );
endmodule

project/m4/tb/tb_top.sv
`timescale 1ns/1ps
module tb_top;
  reg         clk, rst;
  reg  [31:0] s_axil_awaddr;
  reg         s_axil_awvalid;
  wire        s_axil_awready;
  reg  [31:0] s_axil_wdata;
  reg  [3:0]  s_axil_wstrb;
  reg         s_axil_wvalid;
  wire        s_axil_wready;
  wire [1:0]  s_axil_bresp;
  wire        s_axil_bvalid;
  reg         s_axil_bready;
  reg  [31:0] s_axil_araddr;
  reg         s_axil_arvalid;
  wire        s_axil_arready;
  wire [31:0] s_axil_rdata;
  wire [1:0]  s_axil_rresp;
  wire        s_axil_rvalid;
  reg         s_axil_rready;
  wire        done;
  wire        busy;
  conv2d_top #(
    .H_IN(5),.W_IN(5),.K(3),
    .H_OUT(1),.W_OUT(1),
    .C_IN(1),.C_OUT(1),
    .SHIFT_BITS(0)
  ) dut (
    .clk(clk),.rst(rst),
    .s_axil_awaddr(s_axil_awaddr),
    .s_axil_awvalid(s_axil_awvalid),
    .s_axil_awready(s_axil_awready),
    .s_axil_wdata(s_axil_wdata),
    .s_axil_wstrb(s_axil_wstrb),
    .s_axil_wvalid(s_axil_wvalid),
    .s_axil_wready(s_axil_wready),
    .s_axil_bresp(s_axil_bresp),
    .s_axil_bvalid(s_axil_bvalid),
    .s_axil_bready(s_axil_bready),
    .s_axil_araddr(s_axil_araddr),
    .s_axil_arvalid(s_axil_arvalid),
    .s_axil_arready(s_axil_arready),
    .s_axil_rdata(s_axil_rdata),
    .s_axil_rresp(s_axil_rresp),
    .s_axil_rvalid(s_axil_rvalid),
    .s_axil_rready(s_axil_rready),
    .done(done),
    .busy(busy)
  );
  initial clk=0;
  always #5 clk=~clk;
  initial begin
    $dumpfile("final_waveform.vcd");
    $dumpvars(0,tb_top);
  end
  task axi_write;
    input [31:0] addr;
    input [31:0] data;
    begin
      @(posedge clk);
      s_axil_awaddr=addr; s_axil_awvalid=1;
      s_axil_wdata=data;  s_axil_wstrb=4'hF;
      s_axil_wvalid=1;    s_axil_bready=1;
      @(posedge clk);
      s_axil_awvalid=0; s_axil_wvalid=0;
      @(posedge clk);
    end
  endtask
  task axi_read;
    input  [31:0] addr;
    output [31:0] data;
    begin
      @(posedge clk);
      s_axil_araddr=addr; s_axil_arvalid=1;
      s_axil_rready=1;
      @(posedge clk);
      s_axil_arvalid=0;
      @(posedge clk);
      data=s_axil_rdata;
    end
  endtask
  reg signed [7:0] act_vals [0:24];
  reg signed [7:0] wt_vals  [0:8];
  reg signed [7:0] EXPECTED;
  reg [31:0] result;
  integer i;
  initial begin
    act_vals[0]=8'sd1;  act_vals[1]=8'sd2;  act_vals[2]=8'sd3;
    act_vals[3]=8'sd4;  act_vals[4]=8'sd5;
    act_vals[5]=8'sd1;  act_vals[6]=8'sd2;  act_vals[7]=8'sd3;
    act_vals[8]=8'sd4;  act_vals[9]=8'sd5;
    act_vals[10]=8'sd1; act_vals[11]=8'sd2; act_vals[12]=8'sd3;
    act_vals[13]=8'sd4; act_vals[14]=8'sd5;
    act_vals[15]=8'sd1; act_vals[16]=8'sd2; act_vals[17]=8'sd3;
    act_vals[18]=8'sd4; act_vals[19]=8'sd5;
    act_vals[20]=8'sd1; act_vals[21]=8'sd2; act_vals[22]=8'sd3;
    act_vals[23]=8'sd4; act_vals[24]=8'sd5;
    wt_vals[0]=8'sd1;  wt_vals[1]=8'sd0;  wt_vals[2]=-8'sd1;
    wt_vals[3]=8'sd1;  wt_vals[4]=8'sd0;  wt_vals[5]=-8'sd1;
    wt_vals[6]=8'sd1;  wt_vals[7]=8'sd0;  wt_vals[8]=-8'sd1;
    EXPECTED=-8'sd6;
    s_axil_awaddr=0; s_axil_awvalid=0;
    s_axil_wdata=0;  s_axil_wstrb=0; s_axil_wvalid=0;
    s_axil_bready=0;
    s_axil_araddr=0; s_axil_arvalid=0; s_axil_rready=0;
    rst=1;
    repeat(4) @(posedge clk);
    rst=0;
    @(posedge clk);
    $display("[TB] HOST WRITE: scale_shift=0 via AXI");
    axi_write(32'h008, 32'd0);
    $display("[TB] HOST WRITE: activations via AXI");
    for (i=0;i<25;i=i+1)
      axi_write(32'h100+i*4,{{24{act_vals[i][7]}},act_vals[i]});
    $display("[TB] HOST WRITE: weights via AXI");
    for (i=0;i<9;i=i+1)
      axi_write(32'h200+i*4,{{24{wt_vals[i][7]}},wt_vals[i]});
    $display("[TB] HOST WRITE: bias=0 via AXI");
    axi_write(32'h300, 32'd0);
    $display("[TB] HOST WRITE: start=1 via AXI");
    axi_write(32'h000, 32'd1);
    $display("[TB] COMPUTE: waiting for done");
    @(posedge done);
    repeat(5) @(posedge clk);
    $display("[TB] HOST READ: result via AXI addr 0x400");
    axi_read(32'h400, result);
    $display("[TB] Expected output[0,0] = %0d", $signed(EXPECTED));
    $display("[TB] Actual   output[0,0] = %0d", $signed(result[7:0]));
    if ($signed(result[7:0])===$signed(EXPECTED))
      $display("PASS: INT8 Conv2D output matches expected value %0d",
               $signed(EXPECTED));
    else
      $display("FAIL: expected %0d but got %0d",
               $signed(EXPECTED),$signed(result[7:0]));
    $display("[TB] HOST WRITE: start=0, returning to IDLE");
    axi_write(32'h000, 32'd0);
    repeat(5) @(posedge clk);
    $finish;
  end
  initial begin
    #10_000_000;
    $display("FAIL: simulation timeout");
    $finish;
  end
endmodule

project/m4/sim/final_waveform.vcd
$date
	Sun Jun  7 03:40:36 2026
$end
$version
	Icarus Verilog
$end
$timescale
	1ps
$end
$scope module tb_top $end
$var wire 1 ! s_axil_wready $end
$var wire 1 " s_axil_rvalid $end
$var wire 2 # s_axil_rresp [1:0] $end
$var wire 32 $ s_axil_rdata [31:0] $end
$var wire 1 % s_axil_bvalid $end
$var wire 2 & s_axil_bresp [1:0] $end
$var wire 1 ' s_axil_awready $end
$var wire 1 ( s_axil_arready $end
$var wire 1 ) done $end
$var wire 1 * busy $end
$var reg 8 + EXPECTED [7:0] $end
$var reg 1 , clk $end
$var reg 32 - result [31:0] $end
$var reg 1 . rst $end
$var reg 32 / s_axil_araddr [31:0] $end
$var reg 1 0 s_axil_arvalid $end
$var reg 32 1 s_axil_awaddr [31:0] $end
$var reg 1 2 s_axil_awvalid $end
$var reg 1 3 s_axil_bready $end
$var reg 1 4 s_axil_rready $end
$var reg 32 5 s_axil_wdata [31:0] $end
$var reg 4 6 s_axil_wstrb [3:0] $end
$var reg 1 7 s_axil_wvalid $end
$var integer 32 8 i [31:0] $end
$scope module dut $end
$var wire 1 , clk $end
$var wire 1 9 compute_done $end
$var wire 8 : mac_a0 [7:0] $end
$var wire 8 ; mac_a1 [7:0] $end
$var wire 8 < mac_a2 [7:0] $end
$var wire 8 = mac_a3 [7:0] $end
$var wire 8 > mac_a4 [7:0] $end
$var wire 8 ? mac_a5 [7:0] $end
$var wire 8 @ mac_a6 [7:0] $end
$var wire 8 A mac_a7 [7:0] $end
$var wire 8 B mac_a8 [7:0] $end
$var wire 8 C mac_b0 [7:0] $end
$var wire 8 D mac_b1 [7:0] $end
$var wire 8 E mac_b2 [7:0] $end
$var wire 8 F mac_b3 [7:0] $end
$var wire 8 G mac_b4 [7:0] $end
$var wire 8 H mac_b5 [7:0] $end
$var wire 8 I mac_b6 [7:0] $end
$var wire 8 J mac_b7 [7:0] $end
$var wire 8 K mac_b8 [7:0] $end
$var wire 1 . rst $end
$var wire 32 L s_axil_araddr [31:0] $end
$var wire 1 0 s_axil_arvalid $end
$var wire 32 M s_axil_awaddr [31:0] $end
$var wire 1 2 s_axil_awvalid $end
$var wire 1 3 s_axil_bready $end
$var wire 1 4 s_axil_rready $end
$var wire 32 N s_axil_wdata [31:0] $end
$var wire 4 O s_axil_wstrb [3:0] $end
$var wire 1 7 s_axil_wvalid $end
$var wire 1 P req_valid $end
$var wire 8 Q req_out [7:0] $end
$var wire 32 R req_in [31:0] $end
$var wire 32 S mac_out [31:0] $end
$var wire 1 T mac_en $end
$var wire 5 U base2 [4:0] $end
$var wire 5 V base1 [4:0] $end
$var wire 5 W base0 [4:0] $end
$var reg 1 * busy $end
$var reg 1 X compute_valid $end
$var reg 1 ) done $end
$var reg 5 Y h_cnt [4:0] $end
$var reg 3 Z next_state [2:0] $end
$var reg 3 [ oc_cnt [2:0] $end
$var reg 32 \ reg_scale_shift [31:0] $end
$var reg 1 ] reg_start $end
$var reg 1 ( s_axil_arready $end
$var reg 1 ' s_axil_awready $end
$var reg 2 ^ s_axil_bresp [1:0] $end
$var reg 1 % s_axil_bvalid $end
$var reg 32 _ s_axil_rdata [31:0] $end
$var reg 2 ` s_axil_rresp [1:0] $end
$var reg 1 " s_axil_rvalid $end
$var reg 1 ! s_axil_wready $end
$var reg 3 a state [2:0] $end
$var reg 5 b w_cnt [4:0] $end
$scope module u_mac $end
$var wire 8 c a0 [7:0] $end
$var wire 8 d a1 [7:0] $end
$var wire 8 e a2 [7:0] $end
$var wire 8 f a3 [7:0] $end
$var wire 8 g a4 [7:0] $end
$var wire 8 h a5 [7:0] $end
$var wire 8 i a6 [7:0] $end
$var wire 8 j a7 [7:0] $end
$var wire 8 k a8 [7:0] $end
$var wire 8 l b0 [7:0] $end
$var wire 8 m b1 [7:0] $end
$var wire 8 n b2 [7:0] $end
$var wire 8 o b3 [7:0] $end
$var wire 8 p b4 [7:0] $end
$var wire 8 q b5 [7:0] $end
$var wire 8 r b6 [7:0] $end
$var wire 8 s b7 [7:0] $end
$var wire 8 t b8 [7:0] $end
$var wire 1 , clk $end
$var wire 1 T en $end
$var wire 1 . rst $end
$var wire 16 u p8 [15:0] $end
$var wire 16 v p7 [15:0] $end
$var wire 16 w p6 [15:0] $end
$var wire 16 x p5 [15:0] $end
$var wire 16 y p4 [15:0] $end
$var wire 16 z p3 [15:0] $end
$var wire 16 { p2 [15:0] $end
$var wire 16 | p1 [15:0] $end
$var wire 16 } p0 [15:0] $end
$var reg 32 ~ acc_out [31:0] $end
$upscope $end
$scope module u_req $end
$var wire 1 , clk $end
$var wire 32 !" in_data [31:0] $end
$var wire 1 . rst $end
$var wire 5 "" shift [4:0] $end
$var wire 1 P valid_in $end
$var wire 32 #" shifted [31:0] $end
$var reg 8 $" out_data [7:0] $end
$upscope $end
$upscope $end
$scope task axi_read $end
$var reg 32 %" addr [31:0] $end
$var reg 32 &" data [31:0] $end
$upscope $end
$scope task axi_write $end
$var reg 32 '" addr [31:0] $end
$var reg 32 (" data [31:0] $end
$upscope $end
$upscope $end
$enddefinitions $end
#0
$dumpvars
bx ("
bx '"
bx &"
bx %"
bx $"
bx #"
bx ""
bx !"
bx ~
bx }
bx |
bx {
bx z
bx y
bx x
bx w
bx v
bx u
bx t
bx s
bx r
bx q
bx p
bx o
bx n
bx m
bx l
bx k
bx j
bx i
bx h
bx g
bx f
bx e
bx d
bx c
bx b
bx a
bx `
bx _
bx ^
x]
bx \
bx [
bx Z
bx Y
xX
bx W
bx V
bx U
xT
bx S
bx R
bx Q
xP
b0 O
b0 N
b0 M
b0 L
bx K
bx J
bx I
bx H
bx G
bx F
bx E
bx D
bx C
bx B
bx A
bx @
bx ?
bx >
bx =
bx <
bx ;
bx :
x9
bx 8
07
b0 6
b0 5
04
03
02
b0 1
00
b0 /
1.
bx -
0,
b11111010 +
x*
x)
x(
x'
bx &
x%
bx $
bx #
x"
x!
$end
#5000
09
b0 W
b101 V
b1010 U
b0 ""
b0 Z
b0 S
b0 ~
b0 Q
b0 $"
0T
0P
b0 a
0X
b0 [
b0 b
b0 Y
0*
0)
b0 #
b0 `
b0 $
b0 _
0"
0(
b0 &
b0 ^
0%
0!
0'
b0 \
0]
1,
#10000
0,
#15000
1,
#20000
0,
#25000
1,
#30000
0,
#35000
0.
1,
#40000
0,
#45000
b0 ("
b1000 '"
1,
#50000
0,
#55000
1!
1'
13
17
b1111 6
b1111 O
12
b1000 1
b1000 M
1,
#60000
0,
#65000
1%
07
02
1,
#70000
0,
#75000
0%
0!
0'
b1 ("
b100000000 '"
b0 8
1,
#80000
0,
#85000
1!
1'
17
b1 5
b1 N
12
b100000000 1
b100000000 M
1,
#90000
0,
#95000
1%
b1 :
b1 c
07
02
1,
#100000
0,
#105000
0%
0!
0'
b10 ("
b100000100 '"
b1 8
1,
#110000
0,
#115000
1!
1'
17
b10 5
b10 N
12
b100000100 1
b100000100 M
1,
#120000
0,
#125000
1%
b10 ;
b10 d
07
02
1,
#130000
0,
#135000
0%
0!
0'
b11 ("
b100001000 '"
b10 8
1,
#140000
0,
#145000
1!
1'
17
b11 5
b11 N
12
b100001000 1
b100001000 M
1,
#150000
0,
#155000
1%
b11 <
b11 e
07
02
1,
#160000
0,
#165000
0%
0!
0'
b100 ("
b100001100 '"
b11 8
1,
#170000
0,
#175000
1!
1'
17
b100 5
b100 N
12
b100001100 1
b100001100 M
1,
#180000
0,
#185000
1%
07
02
1,
#190000
0,
#195000
0%
0!
0'
b101 ("
b100010000 '"
b100 8
1,
#200000
0,
#205000
1!
1'
17
b101 5
b101 N
12
b100010000 1
b100010000 M
1,
#210000
0,
#215000
1%
07
02
1,
#220000
0,
#225000
0%
0!
0'
b1 ("
b100010100 '"
b101 8
1,
#230000
0,
#235000
1!
1'
17
b1 5
b1 N
12
b100010100 1
b100010100 M
1,
#240000
0,
#245000
1%
b1 =
b1 f
07
02
1,
#250000
0,
#255000
0%
0!
0'
b10 ("
b100011000 '"
b110 8
1,
#260000
0,
#265000
1!
1'
17
b10 5
b10 N
12
b100011000 1
b100011000 M
1,
#270000
0,
#275000
1%
b10 >
b10 g
07
02
1,
#280000
0,
#285000
0%
0!
0'
b11 ("
b100011100 '"
b111 8
1,
#290000
0,
#295000
1!
1'
17
b11 5
b11 N
12
b100011100 1
b100011100 M
1,
#300000
0,
#305000
1%
b11 ?
b11 h
07
02
1,
#310000
0,
#315000
0%
0!
0'
b100 ("
b100100000 '"
b1000 8
1,
#320000
0,
#325000
1!
1'
17
b100 5
b100 N
12
b100100000 1
b100100000 M
1,
#330000
0,
#335000
1%
07
02
1,
#340000
0,
#345000
0%
0!
0'
b101 ("
b100100100 '"
b1001 8
1,
#350000
0,
#355000
1!
1'
17
b101 5
b101 N
12
b100100100 1
b100100100 M
1,
#360000
0,
#365000
1%
07
02
1,
#370000
0,
#375000
0%
0!
0'
b1 ("
b100101000 '"
b1010 8
1,
#380000
0,
#385000
1!
1'
17
b1 5
b1 N
12
b100101000 1
b100101000 M
1,
#390000
0,
#395000
1%
b1 @
b1 i
07
02
1,
#400000
0,
#405000
0%
0!
0'
b10 ("
b100101100 '"
b1011 8
1,
#410000
0,
#415000
1!
1'
17
b10 5
b10 N
12
b100101100 1
b100101100 M
1,
#420000
0,
#425000
1%
b10 A
b10 j
07
02
1,
#430000
0,
#435000
0%
0!
0'
b11 ("
b100110000 '"
b1100 8
1,
#440000
0,
#445000
1!
1'
17
b11 5
b11 N
12
b100110000 1
b100110000 M
1,
#450000
0,
#455000
1%
b11 B
b11 k
07
02
1,
#460000
0,
#465000
0%
0!
0'
b100 ("
b100110100 '"
b1101 8
1,
#470000
0,
#475000
1!
1'
17
b100 5
b100 N
12
b100110100 1
b100110100 M
1,
#480000
0,
#485000
1%
07
02
1,
#490000
0,
#495000
0%
0!
0'
b101 ("
b100111000 '"
b1110 8
1,
#500000
0,
#505000
1!
1'
17
b101 5
b101 N
12
b100111000 1
b100111000 M
1,
#510000
0,
#515000
1%
07
02
1,
#520000
0,
#525000
0%
0!
0'
b1 ("
b100111100 '"
b1111 8
1,
#530000
0,
#535000
1!
1'
17
b1 5
b1 N
12
b100111100 1
b100111100 M
1,
#540000
0,
#545000
1%
07
02
1,
#550000
0,
#555000
0%
0!
0'
b10 ("
b101000000 '"
b10000 8
1,
#560000
0,
#565000
1!
1'
17
b10 5
b10 N
12
b101000000 1
b101000000 M
1,
#570000
0,
#575000
1%
07
02
1,
#580000
0,
#585000
0%
0!
0'
b11 ("
b101000100 '"
b10001 8
1,
#590000
0,
#595000
1!
1'
17
b11 5
b11 N
12
b101000100 1
b101000100 M
1,
#600000
0,
#605000
1%
07
02
1,
#610000
0,
#615000
0%
0!
0'
b100 ("
b101001000 '"
b10010 8
1,
#620000
0,
#625000
1!
1'
17
b100 5
b100 N
12
b101001000 1
b101001000 M
1,
#630000
0,
#635000
1%
07
02
1,
#640000
0,
#645000
0%
0!
0'
b101 ("
b101001100 '"
b10011 8
1,
#650000
0,
#655000
1!
1'
17
b101 5
b101 N
12
b101001100 1
b101001100 M
1,
#660000
0,
#665000
1%
07
02
1,
#670000
0,
#675000
0%
0!
0'
b1 ("
b101010000 '"
b10100 8
1,
#680000
0,
#685000
1!
1'
17
b1 5
b1 N
12
b101010000 1
b101010000 M
1,
#690000
0,
#695000
1%
07
02
1,
#700000
0,
#705000
0%
0!
0'
b10 ("
b101010100 '"
b10101 8
1,
#710000
0,
#715000
1!
1'
17
b10 5
b10 N
12
b101010100 1
b101010100 M
1,
#720000
0,
#725000
1%
07
02
1,
#730000
0,
#735000
0%
0!
0'
b11 ("
b101011000 '"
b10110 8
1,
#740000
0,
#745000
1!
1'
17
b11 5
b11 N
12
b101011000 1
b101011000 M
1,
#750000
0,
#755000
1%
07
02
1,
#760000
0,
#765000
0%
0!
0'
b100 ("
b101011100 '"
b10111 8
1,
#770000
0,
#775000
1!
1'
17
b100 5
b100 N
12
b101011100 1
b101011100 M
1,
#780000
0,
#785000
1%
07
02
1,
#790000
0,
#795000
0%
0!
0'
b101 ("
b101100000 '"
b11000 8
1,
#800000
0,
#805000
1!
1'
17
b101 5
b101 N
12
b101100000 1
b101100000 M
1,
#810000
0,
#815000
1%
07
02
1,
#820000
0,
#825000
0%
0!
0'
b1 ("
b1000000000 '"
b0 8
1,
#830000
0,
#835000
1!
1'
17
b1 5
b1 N
12
b1000000000 1
b1000000000 M
1,
#840000
0,
#845000
1%
b1 }
b1 C
b1 l
07
02
1,
#850000
0,
#855000
0%
0!
0'
b0 ("
b1000000100 '"
b1 8
1,
#860000
0,
#865000
1!
1'
17
b0 5
b0 N
12
b1000000100 1
b1000000100 M
1,
#870000
0,
#875000
1%
b0 |
b0 D
b0 m
07
02
1,
#880000
0,
#885000
0%
0!
0'
b11111111111111111111111111111111 ("
b1000001000 '"
b10 8
1,
#890000
0,
#895000
1!
1'
17
b11111111111111111111111111111111 5
b11111111111111111111111111111111 N
12
b1000001000 1
b1000001000 M
1,
#900000
0,
#905000
1%
b1111111111111101 {
b11111111 E
b11111111 n
07
02
1,
#910000
0,
#915000
0%
0!
0'
b1 ("
b1000001100 '"
b11 8
1,
#920000
0,
#925000
1!
1'
17
b1 5
b1 N
12
b1000001100 1
b1000001100 M
1,
#930000
0,
#935000
1%
b1 z
b1 F
b1 o
07
02
1,
#940000
0,
#945000
0%
0!
0'
b0 ("
b1000010000 '"
b100 8
1,
#950000
0,
#955000
1!
1'
17
b0 5
b0 N
12
b1000010000 1
b1000010000 M
1,
#960000
0,
#965000
1%
b0 y
b0 G
b0 p
07
02
1,
#970000
0,
#975000
0%
0!
0'
b11111111111111111111111111111111 ("
b1000010100 '"
b101 8
1,
#980000
0,
#985000
1!
1'
17
b11111111111111111111111111111111 5
b11111111111111111111111111111111 N
12
b1000010100 1
b1000010100 M
1,
#990000
0,
#995000
1%
b1111111111111101 x
b11111111 H
b11111111 q
07
02
1,
#1000000
0,
#1005000
0%
0!
0'
b1 ("
b1000011000 '"
b110 8
1,
#1010000
0,
#1015000
1!
1'
17
b1 5
b1 N
12
b1000011000 1
b1000011000 M
1,
#1020000
0,
#1025000
1%
b1 w
b1 I
b1 r
07
02
1,
#1030000
0,
#1035000
0%
0!
0'
b0 ("
b1000011100 '"
b111 8
1,
#1040000
0,
#1045000
1!
1'
17
b0 5
b0 N
12
b1000011100 1
b1000011100 M
1,
#1050000
0,
#1055000
1%
b0 v
b0 J
b0 s
07
02
1,
#1060000
0,
#1065000
0%
0!
0'
b11111111111111111111111111111111 ("
b1000100000 '"
b1000 8
1,
#1070000
0,
#1075000
1!
1'
17
b11111111111111111111111111111111 5
b11111111111111111111111111111111 N
12
b1000100000 1
b1000100000 M
1,
#1080000
0,
#1085000
1%
b1111111111111101 u
b11111111 K
b11111111 t
07
02
1,
#1090000
0,
#1095000
0%
0!
0'
b0 ("
b1100000000 '"
b1001 8
1,
#1100000
0,
#1105000
1!
1'
17
b0 5
b0 N
12
b1100000000 1
b1100000000 M
1,
#1110000
0,
#1115000
1%
b0 #"
b0 R
b0 !"
07
02
1,
#1120000
0,
#1125000
0%
0!
0'
b1 ("
b0 '"
1,
#1130000
0,
#1135000
1!
1'
17
b1 5
b1 N
12
b0 1
b0 M
1,
#1140000
0,
#1145000
b1 Z
1%
1]
07
02
1,
#1150000
0,
#1155000
b10 Z
0%
0!
0'
b1 a
1,
#1160000
0,
#1165000
1T
b10 a
1,
#1170000
0,
#1175000
b11 Z
19
1*
1X
b11111111111111111111111111111010 #"
b11111111111111111111111111111010 R
b11111111111111111111111111111010 !"
b11111111111111111111111111111010 S
b11111111111111111111111111111010 ~
1,
#1180000
0,
#1185000
b100 Z
0T
1P
b11 a
1,
#1190000
0,
#1195000
0*
1)
0P
b100 a
b11111010 Q
b11111010 $"
1,
#1200000
0,
#1205000
1,
#1210000
0,
#1215000
1,
#1220000
0,
#1225000
1,
#1230000
0,
#1235000
1,
#1240000
0,
#1245000
b10000000000 %"
1,
#1250000
0,
#1255000
1(
14
10
b10000000000 /
b10000000000 L
1,
#1260000
0,
#1265000
b11111111111111111111111111111010 $
b11111111111111111111111111111010 _
1"
00
1,
