project/m3/rtl/top.sv
// ============================================================================
// Project  : INT8 Conv2D Hardware Accelerator
// Module   : conv2d_top (Top-Level Integrated Module)
// Course   : ECE 410/510 — Hardware for AI/ML, Spring 2026
// Author   : Sai Ganesh Reddy Charian
// Interface: AXI4-Lite — ALL data and control goes through interface only
//
// Port List:
//   clk              - input  - 1b  - System clock
//   rst              - input  - 1b  - Active-high synchronous reset
//   s_axil_awaddr    - input  - 32b - AXI4-Lite write address
//   s_axil_awvalid   - input  - 1b  - Write address valid
//   s_axil_awready   - output - 1b  - Write address ready
//   s_axil_wdata     - input  - 32b - AXI4-Lite write data
//   s_axil_wstrb     - input  - 4b  - Write strobe
//   s_axil_wvalid    - input  - 1b  - Write data valid
//   s_axil_wready    - output - 1b  - Write data ready
//   s_axil_bresp     - output - 2b  - Write response
//   s_axil_bvalid    - output - 1b  - Write response valid
//   s_axil_bready    - input  - 1b  - Write response ready
//   s_axil_araddr    - input  - 32b - AXI4-Lite read address
//   s_axil_arvalid   - input  - 1b  - Read address valid
//   s_axil_arready   - output - 1b  - Read address ready
//   s_axil_rdata     - output - 32b - AXI4-Lite read data
//   s_axil_rresp     - output - 2b  - Read response
//   s_axil_rvalid    - output - 1b  - Read data valid
//   s_axil_rready    - input  - 1b  - Read data ready
//   done             - output - 1b  - Convolution complete flag
//   busy             - output - 1b  - Accelerator busy flag
//
// Internal Structure:
//   - AXI4-Lite is the ONLY path for all data and control
//   - FSM: IDLE -> LOAD -> COMPUTE -> OUTPUT -> DONE_S
//   - mac_array: 9 parallel INT8 multipliers, INT32 accumulation
//   - requantizer: INT32 -> INT8 arithmetic right shift + saturation
//   - Glue logic: mac_en connects FSM COMPUTE state directly to mac_array.en
//                 req_valid connects FSM OUTPUT state directly to requantizer.valid_in
//                 No FIFOs, no clock-domain crossings, no width converters needed
//
// AXI4-Lite Register Map:
//   0x000 W control (bit0=start)
//   0x004 R status  (bit0=done, bit1=busy)
//   0x008 W scale shift
//   0x100+i*4 W act_buf[i] i=0..24
//   0x200+i*4 W weight_buf[i] i=0..8
//   0x300 W bias_buf[0]
//   0x400 R out_buf[0] result
// ============================================================================
`timescale 1ns/1ps

module conv2d_top #(
  parameter DATA_WIDTH=8, parameter ACC_WIDTH=32,
  parameter C_IN=1,  parameter C_OUT=1,
  parameter H_IN=5,  parameter W_IN=5,
  parameter K=3,     parameter H_OUT=1, parameter W_OUT=1,
  parameter SHIFT_BITS=0
)(
  input  wire        clk, rst,
  input  wire [31:0] s_axil_awaddr,
  input  wire        s_axil_awvalid,
  output reg         s_axil_awready,
  input  wire [31:0] s_axil_wdata,
  input  wire [3:0]  s_axil_wstrb,
  input  wire        s_axil_wvalid,
  output reg         s_axil_wready,
  output reg  [1:0]  s_axil_bresp,
  output reg         s_axil_bvalid,
  input  wire        s_axil_bready,
  input  wire [31:0] s_axil_araddr,
  input  wire        s_axil_arvalid,
  output reg         s_axil_arready,
  output reg  [31:0] s_axil_rdata,
  output reg  [1:0]  s_axil_rresp,
  output reg         s_axil_rvalid,
  input  wire        s_axil_rready,
  output reg         done,
  output reg         busy
);

  localparam IDLE=3'd0,LOAD=3'd1,COMPUTE=3'd2,OUTPUT=3'd3,DONE_S=3'd4;
  reg [2:0] state, next_state;
  reg        reg_start;
  reg [31:0] reg_scale_shift;
  reg [4:0]  h_cnt, w_cnt;
  reg [2:0]  oc_cnt;
  reg        compute_valid;

  wire compute_done;
  assign compute_done = compute_valid &&
                        (h_cnt==H_OUT-1) &&
                        (w_cnt==W_OUT-1) &&
                        (oc_cnt==C_OUT-1);

  reg signed [7:0]  weight_buf [0:8];
  reg signed [7:0]  act_buf    [0:24];
  reg signed [31:0] bias_buf   [0:0];
  reg signed [7:0]  out_buf    [0:0];

  wire signed [7:0]  mac_a0,mac_a1,mac_a2,mac_a3,mac_a4;
  wire signed [7:0]  mac_a5,mac_a6,mac_a7,mac_a8;
  wire signed [7:0]  mac_b0,mac_b1,mac_b2,mac_b3,mac_b4;
  wire signed [7:0]  mac_b5,mac_b6,mac_b7,mac_b8;
  wire signed [31:0] mac_out;
  wire               mac_en;
  wire signed [31:0] req_in;
  wire signed [7:0]  req_out;
  wire               req_valid;

  always @(posedge clk) begin
    if (rst) state <= IDLE;
    else     state <= next_state;
  end

  always @(*) begin
    next_state = state;
    case (state)
      IDLE:    if (reg_start)    next_state = LOAD;
      LOAD:                      next_state = COMPUTE;
      COMPUTE: if (compute_done) next_state = OUTPUT;
      OUTPUT:                    next_state = DONE_S;
      DONE_S:  if (!reg_start)   next_state = IDLE;
      default:                   next_state = IDLE;
    endcase
  end

  always @(posedge clk) begin
    if (rst||state==IDLE||state==LOAD) begin
      h_cnt<=0; w_cnt<=0; oc_cnt<=0; compute_valid<=0;
    end else if (state==COMPUTE) begin
      compute_valid <= 1;
      if (oc_cnt==C_OUT-1) begin
        oc_cnt<=0;
        if (w_cnt==W_OUT-1) begin
          w_cnt<=0;
          if (h_cnt<H_OUT-1) h_cnt<=h_cnt+1;
        end else w_cnt<=w_cnt+1;
      end else oc_cnt<=oc_cnt+1;
    end
  end

  always @(posedge clk) begin
    if (rst) begin done<=0; busy<=0; end
    else begin
      if ((state==OUTPUT)&&(next_state==DONE_S)) done<=1;
      else if (state==IDLE) done<=0;
      busy<=(state==COMPUTE);
    end
  end

  always @(posedge clk) begin
    if (rst) out_buf[0]<=0;
    else if (state==DONE_S) out_buf[0]<=req_out;
  end

  always @(posedge clk) begin
    if (rst) begin
      reg_start<=0; reg_scale_shift<=SHIFT_BITS;
      s_axil_awready<=0; s_axil_wready<=0;
      s_axil_bvalid<=0;  s_axil_bresp<=2'b00;
      s_axil_arready<=0; s_axil_rvalid<=0;
      s_axil_rdata<=0;   s_axil_rresp<=2'b00;
    end else begin
      s_axil_awready<=s_axil_awvalid;
      s_axil_wready <=s_axil_wvalid;
      if (s_axil_wvalid&&s_axil_wready) begin
        if      (s_axil_awaddr==32'h000) reg_start<=s_axil_wdata[0];
        else if (s_axil_awaddr==32'h008) reg_scale_shift<=s_axil_wdata;
        else if (s_axil_awaddr>=32'h100&&s_axil_awaddr<32'h164)
          act_buf[(s_axil_awaddr-32'h100)>>2]<=s_axil_wdata[7:0];
        else if (s_axil_awaddr>=32'h200&&s_axil_awaddr<32'h224)
          weight_buf[(s_axil_awaddr-32'h200)>>2]<=s_axil_wdata[7:0];
        else if (s_axil_awaddr==32'h300) bias_buf[0]<=s_axil_wdata;
        s_axil_bvalid<=1;
      end else if (s_axil_bready) s_axil_bvalid<=0;

      s_axil_arready<=s_axil_arvalid;
      if (s_axil_arvalid&&s_axil_arready) begin
        s_axil_rvalid<=1;
        if      (s_axil_araddr==32'h004)
          s_axil_rdata<={30'h0,busy,done};
        else if (s_axil_araddr==32'h400)
          s_axil_rdata<={{24{out_buf[0][7]}},out_buf[0]};
        else s_axil_rdata<=32'hDEADBEEF;
      end else if (s_axil_rready) s_axil_rvalid<=0;
    end
  end

  assign mac_a0=act_buf[h_cnt*W_IN+w_cnt];
  assign mac_a1=act_buf[h_cnt*W_IN+w_cnt+1];
  assign mac_a2=act_buf[h_cnt*W_IN+w_cnt+2];
  assign mac_a3=act_buf[(h_cnt+1)*W_IN+w_cnt];
  assign mac_a4=act_buf[(h_cnt+1)*W_IN+w_cnt+1];
  assign mac_a5=act_buf[(h_cnt+1)*W_IN+w_cnt+2];
  assign mac_a6=act_buf[(h_cnt+2)*W_IN+w_cnt];
  assign mac_a7=act_buf[(h_cnt+2)*W_IN+w_cnt+1];
  assign mac_a8=act_buf[(h_cnt+2)*W_IN+w_cnt+2];

  assign mac_b0=weight_buf[0]; assign mac_b1=weight_buf[1];
  assign mac_b2=weight_buf[2]; assign mac_b3=weight_buf[3];
  assign mac_b4=weight_buf[4]; assign mac_b5=weight_buf[5];
  assign mac_b6=weight_buf[6]; assign mac_b7=weight_buf[7];
  assign mac_b8=weight_buf[8];

  assign mac_en    = (state==COMPUTE);
  assign req_in    = mac_out + bias_buf[0];
  assign req_valid = (state==OUTPUT);

  mac_array u_mac (
    .clk(clk),.rst(rst),.en(mac_en),
    .a0(mac_a0),.a1(mac_a1),.a2(mac_a2),
    .a3(mac_a3),.a4(mac_a4),.a5(mac_a5),
    .a6(mac_a6),.a7(mac_a7),.a8(mac_a8),
    .b0(mac_b0),.b1(mac_b1),.b2(mac_b2),
    .b3(mac_b3),.b4(mac_b4),.b5(mac_b5),
    .b6(mac_b6),.b7(mac_b7),.b8(mac_b8),
    .acc_out(mac_out)
  );

  requantizer u_req (
    .clk(clk),.rst(rst),
    .in_data(req_in),
    .shift(reg_scale_shift[4:0]),
    .valid_in(req_valid),
    .out_data(req_out)
  );

endmodule

// ============================================================================
// Module: mac_array
// 9 parallel INT8 signed multipliers with INT32 registered accumulator
// All products sign-extended to 32 bits before addition
// ============================================================================
module mac_array (
  input  wire        clk, rst, en,
  input  wire signed [7:0] a0,a1,a2,a3,a4,a5,a6,a7,a8,
  input  wire signed [7:0] b0,b1,b2,b3,b4,b5,b6,b7,b8,
  output reg  signed [31:0] acc_out
);
  wire signed [31:0] p0,p1,p2,p3,p4,p5,p6,p7,p8;
  assign p0={{24{a0[7]}},a0}*{{24{b0[7]}},b0};
  assign p1={{24{a1[7]}},a1}*{{24{b1[7]}},b1};
  assign p2={{24{a2[7]}},a2}*{{24{b2[7]}},b2};
  assign p3={{24{a3[7]}},a3}*{{24{b3[7]}},b3};
  assign p4={{24{a4[7]}},a4}*{{24{b4[7]}},b4};
  assign p5={{24{a5[7]}},a5}*{{24{b5[7]}},b5};
  assign p6={{24{a6[7]}},a6}*{{24{b6[7]}},b6};
  assign p7={{24{a7[7]}},a7}*{{24{b7[7]}},b7};
  assign p8={{24{a8[7]}},a8}*{{24{b8[7]}},b8};
  always @(posedge clk) begin
    if (rst)     acc_out<=0;
    else if (en) acc_out<=p0+p1+p2+p3+p4+p5+p6+p7+p8;
  end
endmodule

// ============================================================================
// Module: requantizer
// INT32 -> INT8 with arithmetic right shift and signed saturation
// Saturates to +127 / -128 on overflow
// ============================================================================
module requantizer (
  input  wire        clk, rst, valid_in,
  input  wire signed [31:0] in_data,
  input  wire [4:0]  shift,
  output reg  signed [7:0]  out_data
);
  wire signed [31:0] shifted;
  assign shifted = in_data >>> shift;
  always @(posedge clk) begin
    if (rst) out_data<=0;
    else if (valid_in) begin
      if      (shifted> 127) out_data<= 8'sd127;
      else if (shifted<-128) out_data<=-8'sd128;
      else                   out_data<=shifted[7:0];
    end
  end
endmodule

project/m3/tb/tb_top.sv
`timescale 1ns/1ps
// ============================================================================
// Module   : tb_top — End-to-End Co-Simulation Testbench
// Course   : ECE 410/510 — Hardware for AI/ML, Spring 2026
// Author   : Sai Ganesh Reddy Charian
//
// Description:
//   All data driven through AXI4-Lite interface only — no direct DUT access.
//   Testbench acts as a host processor sending AXI4-Lite transactions.
//
// Test vector:
//   Activation patch (5x5, top-left 3x3 = [[1,2,3],[4,5,6],[7,8,9]], rest=0)
//   Weight kernel [[1,0,-1],[1,0,-1],[1,0,-1]]
//   Bias = 0, Scale shift = 0
//
// Hand calculation (independent reference, not from prior DUT run):
//   out = 1*1 + 2*0 + 3*(-1)
//       + 4*1 + 5*0 + 6*(-1)
//       + 7*1 + 8*0 + 9*(-1)
//       = (1-3) + (4-6) + (7-9)
//       = -2 + -2 + -2
//       = -6
//   Expected INT8 output = -6 (signed), 8'hFA (hex)
// ============================================================================

module tb_top;

  reg         clk, rst;
  reg  [31:0] s_axil_awaddr;
  reg         s_axil_awvalid;
  wire        s_axil_awready;
  reg  [31:0] s_axil_wdata;
  reg  [3:0]  s_axil_wstrb;
  reg         s_axil_wvalid;
  wire        s_axil_wready;
  wire [1:0]  s_axil_bresp;
  wire        s_axil_bvalid;
  reg         s_axil_bready;
  reg  [31:0] s_axil_araddr;
  reg         s_axil_arvalid;
  wire        s_axil_arready;
  wire [31:0] s_axil_rdata;
  wire [1:0]  s_axil_rresp;
  wire        s_axil_rvalid;
  reg         s_axil_rready;
  wire        done;
  wire        busy;


  localparam signed [7:0] EXPECTED = -8'sd6;

  conv2d_top #(
    .DATA_WIDTH(8),.ACC_WIDTH(32),
    .C_IN(1),.C_OUT(1),
    .H_IN(5),.W_IN(5),
    .K(3),.H_OUT(1),.W_OUT(1),
    .SHIFT_BITS(0)
  ) dut (
    .clk(clk),.rst(rst),
    .s_axil_awaddr(s_axil_awaddr),.s_axil_awvalid(s_axil_awvalid),
    .s_axil_awready(s_axil_awready),
    .s_axil_wdata(s_axil_wdata),.s_axil_wstrb(s_axil_wstrb),
    .s_axil_wvalid(s_axil_wvalid),.s_axil_wready(s_axil_wready),
    .s_axil_bresp(s_axil_bresp),.s_axil_bvalid(s_axil_bvalid),
    .s_axil_bready(s_axil_bready),
    .s_axil_araddr(s_axil_araddr),.s_axil_arvalid(s_axil_arvalid),
    .s_axil_arready(s_axil_arready),
    .s_axil_rdata(s_axil_rdata),.s_axil_rresp(s_axil_rresp),
    .s_axil_rvalid(s_axil_rvalid),.s_axil_rready(s_axil_rready),
    .done(done),.busy(busy)
  );

  initial clk=0;
  always #5 clk=~clk;

  initial begin
    $dumpfile("cosim_waveform.vcd");
    $dumpvars(0,tb_top);
  end

  // AXI4-Lite write task — drives awaddr+wdata through proper handshake
  task axi_write;
    input [31:0] addr;
    input [31:0] data;
    begin
      @(posedge clk);
      s_axil_awaddr<=addr; s_axil_awvalid<=1;
      s_axil_wdata<=data;  s_axil_wstrb<=4'hF;
      s_axil_wvalid<=1;    s_axil_bready<=1;
      @(posedge clk);
      @(posedge clk);
      @(posedge clk);
      s_axil_awvalid<=0; s_axil_wvalid<=0;
      @(posedge clk);
      s_axil_bready<=0;
      @(posedge clk);
    end
  endtask

  // AXI4-Lite read task — drives araddr and captures rdata through handshake
  task axi_read;
    input  [31:0] addr;
    output [31:0] rdata;
    begin
      @(posedge clk);
      s_axil_araddr<=addr; s_axil_arvalid<=1; s_axil_rready<=1;
      @(posedge clk);
      @(posedge clk);
      @(posedge clk);
      rdata=s_axil_rdata;
      s_axil_arvalid<=0; s_axil_rready<=0;
      @(posedge clk);
    end
  endtask

  integer i;
  reg [31:0] result;
  reg signed [7:0] act_vals [0:24];
  reg signed [7:0] wt_vals  [0:8];

  initial begin
    // ---- RESET PHASE ----
    rst=1;
    s_axil_awaddr=0; s_axil_awvalid=0;
    s_axil_wdata=0;  s_axil_wstrb=0; s_axil_wvalid=0;
    s_axil_bready=0; s_axil_araddr=0; s_axil_arvalid=0;
    s_axil_rready=0; result=0;

    repeat(5) @(posedge clk);
    rst=0;
    repeat(2) @(posedge clk);

    // ---- LOAD TEST VECTORS ----
    // 5x5 activation map — top-left 3x3 = [[1,2,3],[4,5,6],[7,8,9]], rest=0
    act_vals[0]=8'sd1;  act_vals[1]=8'sd2;  act_vals[2]=8'sd3;
    act_vals[3]=8'sd0;  act_vals[4]=8'sd0;
    act_vals[5]=8'sd4;  act_vals[6]=8'sd5;  act_vals[7]=8'sd6;
    act_vals[8]=8'sd0;  act_vals[9]=8'sd0;
    act_vals[10]=8'sd7; act_vals[11]=8'sd8; act_vals[12]=8'sd9;
    act_vals[13]=8'sd0; act_vals[14]=8'sd0;
    act_vals[15]=0; act_vals[16]=0; act_vals[17]=0;
    act_vals[18]=0; act_vals[19]=0; act_vals[20]=0;
    act_vals[21]=0; act_vals[22]=0; act_vals[23]=0; act_vals[24]=0;

    // 3x3 weight kernel [[1,0,-1],[1,0,-1],[1,0,-1]] — vertical edge detector
    wt_vals[0]=8'sd1;  wt_vals[1]=8'sd0;  wt_vals[2]=-8'sd1;
    wt_vals[3]=8'sd1;  wt_vals[4]=8'sd0;  wt_vals[5]=-8'sd1;
    wt_vals[6]=8'sd1;  wt_vals[7]=8'sd0;  wt_vals[8]=-8'sd1;

    // ---- HOST WRITE PHASE — ALL through AXI4-Lite ----
    $display("[TB] HOST WRITE: scale_shift=0 via AXI");
    axi_write(32'h008, 32'd0);

    $display("[TB] HOST WRITE: activations via AXI");
    begin : load_act
      reg [31:0] act_word;
      for (i=0;i<25;i=i+1) begin
        act_word={{24{act_vals[i][7]}},act_vals[i]};
        axi_write(32'h100+i*4, act_word);
      end
    end

    $display("[TB] HOST WRITE: weights via AXI");
    begin : load_wt
      reg [31:0] wt_word;
      for (i=0;i<9;i=i+1) begin
        wt_word={{24{wt_vals[i][7]}},wt_vals[i]};
        axi_write(32'h200+i*4, wt_word);
      end
    end

    $display("[TB] HOST WRITE: bias=0 via AXI");
    axi_write(32'h300, 32'd0);

    $display("[TB] HOST WRITE: start=1 via AXI");
    axi_write(32'h000, 32'd1);

    // ---- COMPUTE PHASE — wait for done signal ----
    $display("[TB] COMPUTE: waiting for done");
    @(posedge done);
    repeat(5) @(posedge clk);

    // ---- HOST READ PHASE — result through AXI4-Lite ----
    $display("[TB] HOST READ: result via AXI addr 0x400");
    axi_read(32'h400, result);

    $display("[TB] Expected output[0,0] = %0d", $signed(EXPECTED));
    $display("[TB] Actual   output[0,0] = %0d", $signed(result[7:0]));

    // ---- PASS/FAIL COMPARISON ----
    if ($signed(result[7:0]) === $signed(EXPECTED))
      $display("PASS: INT8 Conv2D output matches expected value %0d", $signed(EXPECTED));
    else
      $display("FAIL: expected %0d but got %0d",
               $signed(EXPECTED), $signed(result[7:0]));

    // ---- RETURN TO IDLE ----
    $display("[TB] HOST WRITE: start=0, returning to IDLE");
    axi_write(32'h000, 32'd0);
    repeat(5) @(posedge clk);
    $finish;
  end

  // Timeout guard — prevents infinite hang if DUT never raises done
  initial begin
    #10000000;
    $display("FAIL: simulation timeout");
    $finish;
  end

endmodule

project/m3/sim/cosim_waveform.vcd
$date
	Sat May 23 22:24:31 2026
$end
$version
	Icarus Verilog
$end
$timescale
	1ps
$end
$scope module tb_top $end
$var wire 1 ! s_axil_wready $end
$var wire 1 " s_axil_rvalid $end
$var wire 2 # s_axil_rresp [1:0] $end
$var wire 32 $ s_axil_rdata [31:0] $end
$var wire 1 % s_axil_bvalid $end
$var wire 2 & s_axil_bresp [1:0] $end
$var wire 1 ' s_axil_awready $end
$var wire 1 ( s_axil_arready $end
$var wire 1 ) done $end
$var wire 1 * busy $end
$var reg 1 + clk $end
$var reg 32 , result [31:0] $end
$var reg 1 - rst $end
$var reg 32 . s_axil_araddr [31:0] $end
$var reg 1 / s_axil_arvalid $end
$var reg 32 0 s_axil_awaddr [31:0] $end
$var reg 1 1 s_axil_awvalid $end
$var reg 1 2 s_axil_bready $end
$var reg 1 3 s_axil_rready $end
$var reg 32 4 s_axil_wdata [31:0] $end
$var reg 4 5 s_axil_wstrb [3:0] $end
$var reg 1 6 s_axil_wvalid $end
$var integer 32 7 i [31:0] $end
$scope module dut $end
$var wire 1 + clk $end
$var wire 1 8 compute_done $end
$var wire 8 9 mac_a0 [7:0] $end
$var wire 8 : mac_a1 [7:0] $end
$var wire 8 ; mac_a2 [7:0] $end
$var wire 8 < mac_a3 [7:0] $end
$var wire 8 = mac_a4 [7:0] $end
$var wire 8 > mac_a5 [7:0] $end
$var wire 8 ? mac_a6 [7:0] $end
$var wire 8 @ mac_a7 [7:0] $end
$var wire 8 A mac_a8 [7:0] $end
$var wire 8 B mac_b0 [7:0] $end
$var wire 8 C mac_b1 [7:0] $end
$var wire 8 D mac_b2 [7:0] $end
$var wire 8 E mac_b3 [7:0] $end
$var wire 8 F mac_b4 [7:0] $end
$var wire 8 G mac_b5 [7:0] $end
$var wire 8 H mac_b6 [7:0] $end
$var wire 8 I mac_b7 [7:0] $end
$var wire 8 J mac_b8 [7:0] $end
$var wire 1 - rst $end
$var wire 32 K s_axil_araddr [31:0] $end
$var wire 1 / s_axil_arvalid $end
$var wire 32 L s_axil_awaddr [31:0] $end
$var wire 1 1 s_axil_awvalid $end
$var wire 1 2 s_axil_bready $end
$var wire 1 3 s_axil_rready $end
$var wire 32 M s_axil_wdata [31:0] $end
$var wire 4 N s_axil_wstrb [3:0] $end
$var wire 1 6 s_axil_wvalid $end
$var wire 1 O req_valid $end
$var wire 8 P req_out [7:0] $end
$var wire 32 Q req_in [31:0] $end
$var wire 32 R mac_out [31:0] $end
$var wire 1 S mac_en $end
$var reg 1 * busy $end
$var reg 1 T compute_valid $end
$var reg 1 ) done $end
$var reg 5 U h_cnt [4:0] $end
$var reg 3 V next_state [2:0] $end
$var reg 3 W oc_cnt [2:0] $end
$var reg 32 X reg_scale_shift [31:0] $end
$var reg 1 Y reg_start $end
$var reg 1 ( s_axil_arready $end
$var reg 1 ' s_axil_awready $end
$var reg 2 Z s_axil_bresp [1:0] $end
$var reg 1 % s_axil_bvalid $end
$var reg 32 [ s_axil_rdata [31:0] $end
$var reg 2 \ s_axil_rresp [1:0] $end
$var reg 1 " s_axil_rvalid $end
$var reg 1 ! s_axil_wready $end
$var reg 3 ] state [2:0] $end
$var reg 5 ^ w_cnt [4:0] $end
$scope module u_mac $end
$var wire 8 _ a0 [7:0] $end
$var wire 8 ` a1 [7:0] $end
$var wire 8 a a2 [7:0] $end
$var wire 8 b a3 [7:0] $end
$var wire 8 c a4 [7:0] $end
$var wire 8 d a5 [7:0] $end
$var wire 8 e a6 [7:0] $end
$var wire 8 f a7 [7:0] $end
$var wire 8 g a8 [7:0] $end
$var wire 8 h b0 [7:0] $end
$var wire 8 i b1 [7:0] $end
$var wire 8 j b2 [7:0] $end
$var wire 8 k b3 [7:0] $end
$var wire 8 l b4 [7:0] $end
$var wire 8 m b5 [7:0] $end
$var wire 8 n b6 [7:0] $end
$var wire 8 o b7 [7:0] $end
$var wire 8 p b8 [7:0] $end
$var wire 1 + clk $end
$var wire 1 S en $end
$var wire 1 - rst $end
$var wire 32 q p8 [31:0] $end
$var wire 32 r p7 [31:0] $end
$var wire 32 s p6 [31:0] $end
$var wire 32 t p5 [31:0] $end
$var wire 32 u p4 [31:0] $end
$var wire 32 v p3 [31:0] $end
$var wire 32 w p2 [31:0] $end
$var wire 32 x p1 [31:0] $end
$var wire 32 y p0 [31:0] $end
$var reg 32 z acc_out [31:0] $end
$upscope $end
$scope module u_req $end
$var wire 1 + clk $end
$var wire 32 { in_data [31:0] $end
$var wire 1 - rst $end
$var wire 5 | shift [4:0] $end
$var wire 1 O valid_in $end
$var wire 32 } shifted [31:0] $end
$var reg 8 ~ out_data [7:0] $end
$upscope $end
$upscope $end
$scope begin load_act $end
$var reg 32 !" act_word [31:0] $end
$upscope $end
$scope begin load_wt $end
$var reg 32 "" wt_word [31:0] $end
$upscope $end
$scope task axi_read $end
$var reg 32 #" addr [31:0] $end
$var reg 32 $" rdata [31:0] $end
$upscope $end
$scope task axi_write $end
$var reg 32 %" addr [31:0] $end
$var reg 32 &" data [31:0] $end
$upscope $end
$upscope $end
$enddefinitions $end
#0
$dumpvars
bx &"
bx %"
bx $"
bx #"
bx ""
bx !"
bx ~
bx }
bx |
bx {
bx z
bx y
bx x
bx w
bx v
bx u
bx t
bx s
bx r
bx q
bx p
bx o
bx n
bx m
bx l
bx k
bx j
bx i
bx h
bx g
bx f
bx e
bx d
bx c
bx b
bx a
bx `
bx _
bx ^
bx ]
bx \
bx [
bx Z
xY
bx X
bx W
bx V
bx U
xT
xS
bx R
bx Q
bx P
xO
b0 N
b0 M
b0 L
b0 K
bx J
bx I
bx H
bx G
bx F
bx E
bx D
bx C
bx B
bx A
bx @
bx ?
bx >
bx =
bx <
bx ;
bx :
bx 9
x8
bx 7
06
b0 5
b0 4
03
02
01
b0 0
0/
b0 .
1-
b0 ,
0+
x*
x)
x(
x'
bx &
x%
bx $
bx #
x"
x!
$end
#5000
08
b0 |
b0 V
b0 R
b0 z
b0 P
b0 ~
0S
0O
b0 ]
0T
b0 W
b0 ^
b0 U
0*
0)
b0 #
b0 \
b0 $
b0 [
0"
0(
b0 &
b0 Z
0%
0!
0'
b0 X
0Y
1+
#10000
0+
#15000
1+
#20000
0+
#25000
1+
#30000
0+
#35000
1+
#40000
0+
#45000
0-
1+
#50000
0+
#55000
1+
#60000
0+
#65000
b0 &"
b1000 %"
1+
#70000
0+
#75000
12
16
b1111 5
b1111 N
11
b1000 0
b1000 L
1+
#80000
0+
#85000
1!
1'
1+
#90000
0+
#95000
1%
1+
#100000
0+
#105000
06
01
1+
#110000
0+
#115000
0%
0!
0'
02
1+
#120000
0+
#125000
b1 &"
b100000000 %"
b1 !"
b0 7
1+
#130000
0+
#135000
12
16
b1 4
b1 M
11
b100000000 0
b100000000 L
1+
#140000
0+
#145000
1!
1'
1+
#150000
0+
#155000
1%
b1 9
b1 _
1+
#160000
0+
#165000
06
01
1+
#170000
0+
#175000
0%
0!
0'
02
1+
#180000
0+
#185000
b10 &"
b100000100 %"
b10 !"
b1 7
1+
#190000
0+
#195000
12
16
b10 4
b10 M
11
b100000100 0
b100000100 L
1+
#200000
0+
#205000
1!
1'
1+
#210000
0+
#215000
1%
b10 :
b10 `
1+
#220000
0+
#225000
06
01
1+
#230000
0+
#235000
0%
0!
0'
02
1+
#240000
0+
#245000
b11 &"
b100001000 %"
b11 !"
b10 7
1+
#250000
0+
#255000
12
16
b11 4
b11 M
11
b100001000 0
b100001000 L
1+
#260000
0+
#265000
1!
1'
1+
#270000
0+
#275000
1%
b11 ;
b11 a
1+
#280000
0+
#285000
06
01
1+
#290000
0+
#295000
0%
0!
0'
02
1+
#300000
0+
#305000
b0 &"
b100001100 %"
b0 !"
b11 7
1+
#310000
0+
#315000
12
16
b0 4
b0 M
11
b100001100 0
b100001100 L
1+
#320000
0+
#325000
1!
1'
1+
#330000
0+
#335000
1%
1+
#340000
0+
#345000
06
01
1+
#350000
0+
#355000
0%
0!
0'
02
1+
#360000
0+
#365000
b100010000 %"
b100 7
1+
#370000
0+
#375000
12
16
11
b100010000 0
b100010000 L
1+
#380000
0+
#385000
1!
1'
1+
#390000
0+
#395000
1%
1+
#400000
0+
#405000
06
01
1+
#410000
0+
#415000
0%
0!
0'
02
1+
#420000
0+
#425000
b100 &"
b100010100 %"
b100 !"
b101 7
1+
#430000
0+
#435000
12
16
b100 4
b100 M
11
b100010100 0
b100010100 L
1+
#440000
0+
#445000
1!
1'
1+
#450000
0+
#455000
1%
b100 <
b100 b
1+
#460000
0+
#465000
06
01
1+
#470000
0+
#475000
0%
0!
0'
02
1+
#480000
0+
#485000
b101 &"
b100011000 %"
b101 !"
b110 7
1+
#490000
0+
#495000
12
16
b101 4
b101 M
11
b100011000 0
b100011000 L
1+
#500000
0+
#505000
1!
1'
1+
#510000
0+
#515000
1%
b101 =
b101 c
1+
#520000
0+
#525000
06
01
1+
#530000
0+
#535000
0%
0!
0'
02
1+
#540000
0+
#545000
b110 &"
b100011100 %"
b110 !"
b111 7
1+
#550000
0+
#555000
12
16
b110 4
b110 M
11
b100011100 0
b100011100 L
1+
#560000
0+
#565000
1!
1'
1+
#570000
0+
#575000
1%
b110 >
b110 d
1+
#580000
0+
#585000
06
01
1+
#590000
0+
#595000
0%
0!
0'
02
1+
#600000
0+
#605000
b0 &"
b100100000 %"
b0 !"
b1000 7
1+
#610000
0+
#615000
12
16
b0 4
b0 M
11
b100100000 0
b100100000 L
1+
#620000
0+
#625000
1!
1'
1+
#630000
0+
#635000
1%
1+
#640000
0+
#645000
06
01
1+
#650000
0+
#655000
0%
0!
0'
02
1+
#660000
0+
#665000
b100100100 %"
b1001 7
1+
#670000
0+
#675000
12
16
11
b100100100 0
b100100100 L
1+
#680000
0+
#685000
1!
1'
1+
#690000
0+
#695000
1%
1+
#700000
0+
#705000
06
01
1+
#710000
0+
#715000
0%
0!
0'
02
1+
#720000
0+
#725000
b111 &"
b100101000 %"
b111 !"
b1010 7
1+
#730000
0+
#735000
12
16
b111 4
b111 M
11
b100101000 0
b100101000 L
1+
#740000
0+
#745000
1!
1'
1+
#750000
0+
#755000
1%
b111 ?
b111 e
1+
#760000
0+
#765000
06
01
1+
#770000
0+
#775000
0%
0!
0'
02
1+
#780000
0+
#785000
b1000 &"
b100101100 %"
b1000 !"
b1011 7
1+
#790000
0+
#795000
12
16
b1000 4
b1000 M
11
b100101100 0
b100101100 L
1+
#800000
0+
#805000
1!
1'
1+
#810000
0+
#815000
1%
b1000 @
b1000 f
1+
#820000
0+
#825000
06
01
1+
#830000
0+
#835000
0%
0!
0'
02
1+
#840000
0+
#845000
b1001 &"
b100110000 %"
b1001 !"
b1100 7
1+
#850000
0+
#855000
12
16
b1001 4
b1001 M
11
b100110000 0
b100110000 L
1+
#860000
0+
#865000
1!
1'
1+
#870000
0+
#875000
1%
b1001 A
b1001 g
1+
#880000
0+
#885000
06
01
1+
#890000
0+
#895000
0%
0!
0'
02
1+
#900000
0+
#905000
b0 &"
b100110100 %"
b0 !"
b1101 7
1+
#910000
0+
#915000
12
16
b0 4
b0 M
11
b100110100 0
b100110100 L
1+
#920000
0+
#925000
1!
1'
1+
#930000
0+
#935000
1%
1+
#940000
0+
#945000
06
01
1+
#950000
0+
#955000
0%
0!
0'
02
1+
#960000
0+
#965000
b100111000 %"
b1110 7
1+
#970000
0+
#975000
12
16
11
b100111000 0
b100111000 L
1+
#980000
0+
#985000
1!
1'
1+
#990000
0+
#995000
1%
1+
#1000000
0+
#1005000
06
01
1+
#1010000
0+
#1015000
0%
0!
0'
02
1+
#1020000
0+
#1025000
b100111100 %"
b1111 7
1+
#1030000
0+
#1035000
12
16
11
b100111100 0
b100111100 L
1+
#1040000
0+
#1045000
1!
1'
1+
#1050000
0+
#1055000
1%
1+
#1060000
0+
#1065000
06
01
1+
#1070000
0+
#1075000
0%
0!
0'
02
1+
#1080000
0+
#1085000
b101000000 %"
b10000 7
1+
#1090000
0+
#1095000
12
16
11
b101000000 0
b101000000 L
1+
#1100000
0+
#1105000
1!
1'
1+
#1110000
0+
#1115000
1%
1+
#1120000
0+
